spexmlp_swiglu_cuda_torch24.so
spexmlp/eswiglu.py
spexmlp/_autocast_utils.py
spexmlp/spexmlp.py
spexmlp/__init__.py
spexmlp/rollcat.py
spexmlp-2.0.2.post24.dist-info/WHEEL
spexmlp-2.0.2.post24.dist-info/METADATA
spexmlp-2.0.2.post24.dist-info/RECORD
spexmlp-2.0.2.post24.dist-info/top_level.txt
spexmlp-2.0.2.post24.dist-info/LICENSE
spexmlp.libs/libcudart-d0da41ae.so.11.8.89
