Metadata-Version: 2.1
Name: spexmlp
Version: 2.0.2.post24
Summary: fused modules of EPRI(SGRI) visual models
Home-page: https://github.com/flishwang/spexmlp
Author: flish_wang
Author-email: flish_wang@sina.com
License-File: LICENSE
Requires-Dist: tqdm>=4.28.1
Requires-Dist: numpy>=1.15.3
Requires-Dist: PyYAML>=5.1
Requires-Dist: packaging>=20.6
Requires-Dist: torch<2.5.0,>=2.4.0
